git_narrate/__init__.py
git_narrate/analyzer.py
git_narrate/cli.py
git_narrate/narrator.py
git_narrate/utils.py
git_narrate/visualizer.py
git_narrate-1.0.5.dist-info/licenses/LICENSE
git_narrate-1.0.5.dist-info/METADATA
git_narrate-1.0.5.dist-info/WHEEL
git_narrate-1.0.5.dist-info/entry_points.txt
git_narrate-1.0.5.dist-info/top_level.txt
git_narrate-1.0.5.dist-info/RECORD
