Metadata-Version: 2.4
Name: git-narrate
Version: 1.0.5
Summary: The Repository Storyteller - Analyze git repos and generate development narratives
Home-page: https://github.com/000xs/git-narrate
Author: Sithum Sathsara Rajapakshe | 000x
Author-email: SITHUMSS9122@gmail.com
License: MIT
Project-URL: Bug Tracker, https://github.com/000xs/git-narrate/issues
Project-URL: Documentation, https://github.com/000xs/git-narrate/wiki
Keywords: git version-control repository-analysis storytelling visualization
Classifier: Development Status :: 4 - Beta
Classifier: Intended Audience :: Developers
Classifier: Topic :: Software Development :: Version Control :: Git
Classifier: License :: OSI Approved :: MIT License
Classifier: Programming Language :: Python :: 3
Classifier: Programming Language :: Python :: 3.8
Classifier: Programming Language :: Python :: 3.9
Classifier: Programming Language :: Python :: 3.10
Classifier: Programming Language :: Python :: 3.11
Classifier: Operating System :: OS Independent
Requires-Python: >=3.8
License-File: LICENSE
Requires-Dist: click>=8.2.1
Requires-Dist: rich>=14.1.0
Requires-Dist: GitPython>=3.1.44
Requires-Dist: matplotlib>=3.10.5
Requires-Dist: numpy>=2.3.2
Requires-Dist: openai>=1.99.1
Requires-Dist: python-dotenv>=1.0.1
Requires-Dist: questionary>=2.1.0
Requires-Dist: pyfiglet>=1.0.3
Requires-Dist: requests>=2.28.0
Requires-Dist: markdown2>=2.5.4
Provides-Extra: dev
Requires-Dist: pytest>=7.0.0; extra == "dev"
Requires-Dist: pytest-cov>=4.0.0; extra == "dev"
Requires-Dist: black>=22.0.0; extra == "dev"
Requires-Dist: flake8>=5.0.0; extra == "dev"
Requires-Dist: mypy>=0.991; extra == "dev"
Requires-Dist: pre-commit>=2.20.0; extra == "dev"
Provides-Extra: viz
Requires-Dist: kaleido>=0.2.1; extra == "viz"
Dynamic: author
Dynamic: author-email
Dynamic: classifier
Dynamic: description
Dynamic: description-content-type
Dynamic: home-page
Dynamic: keywords
Dynamic: license
Dynamic: license-file
Dynamic: project-url
Dynamic: provides-extra
Dynamic: requires-dist
Dynamic: requires-python
Dynamic: summary
